{
    "identityPoolName": "demodayproject58d04e29_identitypool_58d04e29",
    "allowUnauthenticatedIdentities": false,
    "resourceNameTruncated": "demoda58d04e29",
    "userPoolName": "demodayproject58d04e29_userpool_58d04e29",
    "autoVerifiedAttributes": [
        "email"
    ],
    "mfaConfiguration": "OFF",
    "mfaTypes": [
        "SMS Text Message"
    ],
    "smsAuthenticationMessage": "Your authentication code is {####}",
    "smsVerificationMessage": "Your verification code is {####}",
    "emailVerificationSubject": "Your verification code",
    "emailVerificationMessage": "Your verification code is {####}",
    "defaultPasswordPolicy": false,
    "passwordPolicyMinLength": 8,
    "passwordPolicyCharacters": [],
    "requiredAttributes": [
        "email"
    ],
    "userpoolClientGenerateSecret": true,
    "userpoolClientRefreshTokenValidity": 30,
    "userpoolClientWriteAttributes": [
        "email"
    ],
    "userpoolClientReadAttributes": [
        "email"
    ],
    "userpoolClientLambdaRole": "demoda58d04e29_userpoolclient_lambda_role",
    "userpoolClientSetAttributes": false,
    "resourceName": "demodayproject58d04e29",
    "authSelections": "identityPoolAndUserPool",
    "authRoleArn": {
        "Fn::GetAtt": [
            "AuthRole",
            "Arn"
        ]
    },
    "unauthRoleArn": {
        "Fn::GetAtt": [
            "UnauthRole",
            "Arn"
        ]
    },
    "useDefault": "defaultSocial",
    "hostedUI": true,
    "usernameAttributes": [
        "email"
    ],
    "triggers": "{\"CustomMessage\":[\"verification-link\"]}",
    "hostedUIDomainName": "demoday2020",
    "authProvidersUserPool": [
        "Google"
    ],
    "hostedUIProviderMeta": "[{\"ProviderName\":\"Google\",\"authorize_scopes\":\"openid email profile\",\"AttributeMapping\":{\"email\":\"email\",\"username\":\"sub\"}}]",
    "oAuthMetadata": "{\"AllowedOAuthFlows\":[\"code\"],\"AllowedOAuthScopes\":[\"phone\",\"email\",\"openid\",\"profile\",\"aws.cognito.signin.user.admin\"],\"CallbackURLs\":[\"https://thewebspace.herokuapp.com/\"],\"LogoutURLs\":[\"https://thewebspace.herokuapp.com/\"]}",
    "userPoolGroupList": [],
    "verificationBucketName": "demodayproject58d04e29verificationbucket",
    "parentStack": {
        "Ref": "AWS::StackId"
    },
    "permissions": [],
    "dependsOn": [
        {
            "category": "function",
            "resourceName": "demodayproject58d04e29CustomMessage",
            "triggerProvider": "Cognito",
            "attributes": [
                "Arn",
                "Name"
            ]
        }
    ]
}